talk2pdf/__init__.py
talk2pdf/__main__.py
talk2pdf/config.py
talk2pdf/t2p_ffmpeg.py
talk2pdf/t2p_openai.py
talk2pdf/t2p_whisper.py
talk2pdf/utils.py
talk2pdf/ytdlp.py
talk2pdf-0.3.0.dist-info/LICENSE
talk2pdf-0.3.0.dist-info/METADATA
talk2pdf-0.3.0.dist-info/WHEEL
talk2pdf-0.3.0.dist-info/top_level.txt
talk2pdf-0.3.0.dist-info/RECORD
