Metadata-Version: 2.1
Name: talk2pdf
Version: 0.3.0
Author-email: Carl Pearson <me@carlpearson.net>
License: 
Project-URL: Bug Tracker, https://github.com/cwpearson/talk2pdf/issues
Project-URL: Homepage, https://github.com/cwpearson/taslk2pdf
Classifier: Programming Language :: Python :: 3
Classifier: License :: OSI Approved :: Apache Software License
Classifier: Operating System :: OS Independent
Classifier: Development Status :: 4 - Beta
Requires-Python: >=3.7
License-File: LICENSE
Requires-Dist: openai (==0.27)
Requires-Dist: pydub
Requires-Dist: imagehash
Requires-Dist: pillow
Requires-Dist: openai-whisper
